pyf.splitter-3.1-py2.7-nspkg.pth
pyf/splitter/__init__.py
pyf/splitter/inputsplitter.py
pyf.splitter-3.1.dist-info/DESCRIPTION.rst
pyf.splitter-3.1.dist-info/METADATA
pyf.splitter-3.1.dist-info/RECORD
pyf.splitter-3.1.dist-info/WHEEL
pyf.splitter-3.1.dist-info/entry_points.txt
pyf.splitter-3.1.dist-info/metadata.json
pyf.splitter-3.1.dist-info/namespace_packages.txt
pyf.splitter-3.1.dist-info/top_level.txt
tests/__init__.py
tests/test_input_splitter.py
