Metadata-Version: 2.0
Name: pyf.splitter
Version: 3.1
Summary: Dataflow splitting system for PyF framework
Home-page: http://pyfproject.org
Author: UNKNOWN
Author-email: UNKNOWN
License: MIT
Platform: UNKNOWN
Classifier: Programming Language :: Python
Requires-Dist: pyjon.utils
Requires-Dist: setuptools
Requires-Dist: six
